ligeor/__init__.py
ligeor/ebai/__init__.py
ligeor/ebai/ebai.py
ligeor/ebai/database/__init__.py
ligeor/ebai/database/generate.py
ligeor/ebai/database/model.py
ligeor/eclipse/__init__.py
ligeor/eclipse/eb_params.py
ligeor/fitting/__init__.py
ligeor/fitting/polyfit.py
ligeor/fitting/sampler.py
ligeor/fitting/twogaussian.py
ligeor/models/__init__.py
ligeor/models/model.py
ligeor/models/polyfit.py
ligeor/models/twogaussian.py
ligeor/utils/__init__.py
ligeor/utils/interactive.py
ligeor/utils/lcutils.py
ligeor/utils/processing.py
ligeor-1.0.2.dist-info/LICENSE
ligeor-1.0.2.dist-info/METADATA
ligeor-1.0.2.dist-info/WHEEL
ligeor-1.0.2.dist-info/top_level.txt
ligeor-1.0.2.dist-info/RECORD
