Metadata-Version: 2.1
Name: ligeor
Version: 1.0.2
Summary: LIght curve GEOmetRy of eclipsing binaries
Home-page: https://github.com/gecheline/ligeor
Author: Angela Kochoska
Author-email: a.kochoska@gmail.com
License: MIT License
Platform: UNKNOWN
License-File: LICENSE
